websiteTest/__init__.py
websiteTest/baseSelenium.py
websiteTest/cli.py
websiteTest/tools.py
websiteTest/websiteTest.py
websiteTest-0.1.2.dist-info/DESCRIPTION.rst
websiteTest-0.1.2.dist-info/METADATA
websiteTest-0.1.2.dist-info/RECORD
websiteTest-0.1.2.dist-info/WHEEL
websiteTest-0.1.2.dist-info/metadata.json
websiteTest-0.1.2.dist-info/top_level.txt
