Metadata-Version: 2.0
Name: websiteTest
Version: 0.1.2
Summary: A package to get visual differences between an expected template image and the actual website’s appearance
Home-page: https://github.com/jotathebest/websiteTest
Author: Jose Reyes Garcia Delgado
Author-email: reyes2000jose@gmail.com
License: GNU General Public License v3
Keywords: websiteTest
Platform: UNKNOWN
Classifier: Development Status :: 2 - Pre-Alpha
Classifier: Intended Audience :: Developers
Classifier: License :: OSI Approved :: GNU General Public License v3 (GPLv3)
Classifier: Natural Language :: English
Classifier: Programming Language :: Python :: 2
Classifier: Programming Language :: Python :: 2.7
Classifier: Programming Language :: Python :: 3
Classifier: Programming Language :: Python :: 3.4
Classifier: Programming Language :: Python :: 3.5
Classifier: Programming Language :: Python :: 3.6
Requires-Dist: Click (>=6.0)
Requires-Dist: imutils (>=0.4.4)
Requires-Dist: selenium (>=3.8.0)
Requires-Dist: opencv-contrib-python (>=3.4.0.12)
Requires-Dist: opencv-python (>=3.4.0.12)
